meshio/__about__.py
meshio/__init__.py
meshio/_common.py
meshio/_exceptions.py
meshio/_files.py
meshio/_helpers.py
meshio/_mesh.py
meshio/_vtk_common.py
meshio/_cli/__init__.py
meshio/_cli/_ascii.py
meshio/_cli/_binary.py
meshio/_cli/_compress.py
meshio/_cli/_convert.py
meshio/_cli/_decompress.py
meshio/_cli/_info.py
meshio/_cli/_main.py
meshio/_cxml/__init__.py
meshio/_cxml/etree.py
meshio/abaqus/__init__.py
meshio/abaqus/_abaqus.py
meshio/ansys/__init__.py
meshio/ansys/_ansys.py
meshio/avsucd/__init__.py
meshio/avsucd/_avsucd.py
meshio/cgns/__init__.py
meshio/cgns/_cgns.py
meshio/dolfin/__init__.py
meshio/dolfin/_dolfin.py
meshio/exodus/__init__.py
meshio/exodus/_exodus.py
meshio/flac3d/__init__.py
meshio/flac3d/_flac3d.py
meshio/gmsh/__init__.py
meshio/gmsh/_gmsh22.py
meshio/gmsh/_gmsh40.py
meshio/gmsh/_gmsh41.py
meshio/gmsh/common.py
meshio/gmsh/main.py
meshio/h5m/__init__.py
meshio/h5m/_h5m.py
meshio/hmf/__init__.py
meshio/hmf/_hmf.py
meshio/mdpa/__init__.py
meshio/mdpa/_mdpa.py
meshio/med/__init__.py
meshio/med/_med.py
meshio/medit/__init__.py
meshio/medit/_medit.py
meshio/medit/_medit_internal.py
meshio/nastran/__init__.py
meshio/nastran/_nastran.py
meshio/netgen/__init__.py
meshio/netgen/_netgen.py
meshio/neuroglancer/__init__.py
meshio/neuroglancer/_neuroglancer.py
meshio/obj/__init__.py
meshio/obj/_obj.py
meshio/off/__init__.py
meshio/off/_off.py
meshio/permas/__init__.py
meshio/permas/_permas.py
meshio/ply/__init__.py
meshio/ply/_ply.py
meshio/stl/__init__.py
meshio/stl/_stl.py
meshio/su2/__init__.py
meshio/su2/_su2.py
meshio/svg/__init__.py
meshio/svg/_svg.py
meshio/tecplot/__init__.py
meshio/tecplot/_tecplot.py
meshio/tetgen/__init__.py
meshio/tetgen/_tetgen.py
meshio/ugrid/__init__.py
meshio/ugrid/_ugrid.py
meshio/vtk/__init__.py
meshio/vtk/_main.py
meshio/vtk/_vtk_42.py
meshio/vtk/_vtk_51.py
meshio/vtp/__init__.py
meshio/vtp/_vtp.py
meshio/vtu/__init__.py
meshio/vtu/_vtu.py
meshio/wkt/__init__.py
meshio/wkt/_wkt.py
meshio/xdmf/__init__.py
meshio2-5.3.6.dist-info/LICENSE.txt
meshio2-5.3.6.dist-info/METADATA
meshio2-5.3.6.dist-info/WHEEL
meshio2-5.3.6.dist-info/entry_points.txt
meshio2-5.3.6.dist-info/top_level.txt
meshio2-5.3.6.dist-info/RECORD
