Metadata-Version: 2.1
Name: meshio2
Version: 5.3.6
Summary: I/O for many mesh formats
Author: Nico Schlömer
Author-email: nico.schloemer@gmail.com
License: The MIT License (MIT)
Project-URL: homepage, https://github.com/finsberg/meshio
Project-URL: code, https://github.com/finsberg/meshio
Project-URL: issues, https://github.com/finsberg/meshio/issues
Keywords: mesh,file formats,scientific,engineering,fem,finite elements
Classifier: Development Status :: 5 - Production/Stable
Classifier: Programming Language :: Python
Classifier: Intended Audience :: Science/Research
Classifier: License :: OSI Approved :: MIT License
Classifier: Operating System :: OS Independent
Classifier: Programming Language :: Python
Classifier: Programming Language :: Python :: 3
Classifier: Programming Language :: Python :: 3.8
Classifier: Programming Language :: Python :: 3.9
Classifier: Programming Language :: Python :: 3.10
Classifier: Programming Language :: Python :: 3.11
Classifier: Programming Language :: Python :: 3.12
Classifier: Topic :: Scientific/Engineering
Classifier: Topic :: Utilities
Requires-Python: >=3.8
License-File: LICENSE.txt
Requires-Dist: numpy>=1.20.0
Requires-Dist: rich
Requires-Dist: importlib-metadata; python_version < "3.8"
Provides-Extra: all
Requires-Dist: netCDF4; extra == "all"
Requires-Dist: h5py; extra == "all"
Provides-Extra: test
Requires-Dist: pytest; extra == "test"
Requires-Dist: pytest-codeblocks>=0.12.1; extra == "test"
Requires-Dist: pytest-cov; extra == "test"
Requires-Dist: meshio2[all]; extra == "test"
